crop_clip/src/__init__.py
crop_clip/src/crop-clip/__init__.py
crop_clip/src/crop-clip/config.py
crop_clip/src/crop-clip/resources/__init__.py
crop_clip/src/crop-clip/resources/args.py
crop_clip/src/crop-clip/resources/cc_types.py
crop_clip/src/crop-clip/resources/files.py
crop_clip/src/crop-clip/resources/utils.py
crop_clip/src/crop-clip/scripts/__init__.py
crop_clip/src/crop-clip/scripts/clip.py
crop_clip/src/crop-clip/scripts/main.py
crop_clippier-0.0.4.dist-info/entry_points.txt
crop_clippier-0.0.4.dist-info/WHEEL
crop_clippier-0.0.4.dist-info/METADATA
crop_clippier-0.0.4.dist-info/RECORD
