Metadata-Version: 2.1
Name: crop-clippier
Version: 0.0.4
Summary: A tool for cropping regions out of volumetric data
Author: Matthew Pimblott
Author-email: Matthew.Pimblott@diamond.ac.uk
Requires-Python: >=3.9,<4.0
Classifier: Programming Language :: Python :: 3
Classifier: Programming Language :: Python :: 3.9
Classifier: Programming Language :: Python :: 3.10
Classifier: Programming Language :: Python :: 3.11
Requires-Dist: Pillow (>=9.4.0,<10.0.0)
Requires-Dist: h5py (>=3.7.0,<4.0.0)
Requires-Dist: numpy (>=1.24.2,<2.0.0)
Requires-Dist: pydantic (>=1.10.7,<2.0.0)
Requires-Dist: tqdm (>=4.65.0,<5.0.0)
